cinemagoerng/__init__.py
cinemagoerng/cli.py
cinemagoerng/linguistics.py
cinemagoerng/lookup.py
cinemagoerng/model.py
cinemagoerng/piculet.py
cinemagoerng/py.typed
cinemagoerng/registry.py
cinemagoerng/specs/title_akas.json
cinemagoerng/specs/title_episodes.json
cinemagoerng/specs/title_episodes_with_pagination.json
cinemagoerng/specs/title_parental_guide.json
cinemagoerng/specs/title_reference.json
cinemagoerng/specs/title_taglines.json
cinemagoerng/web.py
cinemagoerng-0.5.1.dist-info/licenses/LICENSE.txt
cinemagoerng-0.5.1.dist-info/WHEEL
cinemagoerng-0.5.1.dist-info/entry_points.txt
cinemagoerng-0.5.1.dist-info/METADATA
cinemagoerng-0.5.1.dist-info/RECORD
