Metadata-Version: 2.4
Name: cinemagoerng
Version: 0.5.1
Summary: Retrieve data from the IMDb.
Keywords: imdb,cinema,movie,film,cast,actor,director
Author: H. Turgut Uyar, Davide Alberani
Author-email: H. Turgut Uyar <uyar@tekir.org>, Davide Alberani <da@mimante.net>
License-Expression: GPL-3.0-or-later
License-File: LICENSE.txt
Classifier: Development Status :: 3 - Alpha
Classifier: Environment :: Console
Classifier: Intended Audience :: Developers
Classifier: Intended Audience :: End Users/Desktop
Classifier: Natural Language :: English
Classifier: Operating System :: OS Independent
Classifier: Programming Language :: Python
Classifier: Programming Language :: Python :: 3.11
Classifier: Programming Language :: Python :: 3.12
Classifier: Programming Language :: Python :: 3.13
Classifier: Programming Language :: Python :: Implementation :: CPython
Classifier: Programming Language :: Python :: Implementation :: PyPy
Classifier: Topic :: Database :: Front-Ends
Classifier: Topic :: Software Development :: Libraries :: Python Modules
Requires-Dist: typedload~=2.38
Requires-Dist: lxml~=5.4.0
Requires-Dist: jmespath~=1.0.1
Requires-Python: ~=3.11
Project-URL: repository, https://github.com/cinemagoer/cinemagoerng
